babytalk/__init__.py
babytalk/advanced_control_structures.py
babytalk/arithmetic.py
babytalk/control_structures.py
babytalk/data_structures.py
babytalk/error_handling.py
babytalk/file_io.py
babytalk/functions_and_pointers.py
babytalk/gui.py
babytalk-2.2.0.dist-info/LICENSE
babytalk-2.2.0.dist-info/METADATA
babytalk-2.2.0.dist-info/WHEEL
babytalk-2.2.0.dist-info/top_level.txt
babytalk-2.2.0.dist-info/RECORD
