Metadata-Version: 2.1
Name: babytalk
Version: 2.2.0
Summary: A library to simplify Python programming for young learners using natural language commands.
Home-page: https://github.com/Mutaib-yye/babytalk
Author: Mutaib
Author-email: mutaibrather333@gmail.com
License: MIT
Classifier: Programming Language :: Python :: 3
Classifier: License :: OSI Approved :: MIT License
Classifier: Operating System :: OS Independent
Classifier: Intended Audience :: Education
Classifier: Topic :: Education :: Computer Aided Instruction (CAI)
Classifier: Development Status :: 4 - Beta
Requires-Python: >=3.6
License-File: LICENSE
